BottlePythonWebKuangjiaZhongwenWendang/README.md
BottlePythonWebKuangjiaZhongwenWendang/__init__.py
BottlePythonWebKuangjiaZhongwenWendang/__main__.py
BottlePythonWebKuangjiaZhongwenWendang/file.epub
BottlePythonWebKuangjiaZhongwenWendang/index.html
BottlePythonWebKuangjiaZhongwenWendang/css/__init__.py
BottlePythonWebKuangjiaZhongwenWendang/css/annotations.css
BottlePythonWebKuangjiaZhongwenWendang/css/main.css
BottlePythonWebKuangjiaZhongwenWendang/css/normalize.css
BottlePythonWebKuangjiaZhongwenWendang/css/popup.css
BottlePythonWebKuangjiaZhongwenWendang/font/__init__.py
BottlePythonWebKuangjiaZhongwenWendang/font/fontello.eot
BottlePythonWebKuangjiaZhongwenWendang/font/fontello.svg
BottlePythonWebKuangjiaZhongwenWendang/font/fontello.ttf
BottlePythonWebKuangjiaZhongwenWendang/font/fontello.woff
BottlePythonWebKuangjiaZhongwenWendang/img/__init__.py
BottlePythonWebKuangjiaZhongwenWendang/img/annotator-glyph-sprite.png
BottlePythonWebKuangjiaZhongwenWendang/img/annotator-icon-sprite.png
BottlePythonWebKuangjiaZhongwenWendang/img/apple-touch-icon.png
BottlePythonWebKuangjiaZhongwenWendang/img/cancelfullscreen.png
BottlePythonWebKuangjiaZhongwenWendang/img/close.png
BottlePythonWebKuangjiaZhongwenWendang/img/fullscreen.png
BottlePythonWebKuangjiaZhongwenWendang/img/loader.gif
BottlePythonWebKuangjiaZhongwenWendang/img/menu-icon.png
BottlePythonWebKuangjiaZhongwenWendang/img/save.png
BottlePythonWebKuangjiaZhongwenWendang/img/saved.png
BottlePythonWebKuangjiaZhongwenWendang/img/settings-s.png
BottlePythonWebKuangjiaZhongwenWendang/img/settings.png
BottlePythonWebKuangjiaZhongwenWendang/img/star.png
BottlePythonWebKuangjiaZhongwenWendang/js/__init__.py
BottlePythonWebKuangjiaZhongwenWendang/js/epub.js
BottlePythonWebKuangjiaZhongwenWendang/js/epub.min.js
BottlePythonWebKuangjiaZhongwenWendang/js/epub.min.map
BottlePythonWebKuangjiaZhongwenWendang/js/hooks.min.js
BottlePythonWebKuangjiaZhongwenWendang/js/hooks.min.map
bottle_python_web_kuangjia_zhongwen_wendang-2024.3.4.0.dist-info/METADATA
bottle_python_web_kuangjia_zhongwen_wendang-2024.3.4.0.dist-info/WHEEL
bottle_python_web_kuangjia_zhongwen_wendang-2024.3.4.0.dist-info/entry_points.txt
bottle_python_web_kuangjia_zhongwen_wendang-2024.3.4.0.dist-info/top_level.txt
bottle_python_web_kuangjia_zhongwen_wendang-2024.3.4.0.dist-info/RECORD
